arakawa/__init__.py
arakawa/_version.py
arakawa/_version.pyi
arakawa/builtins.py
arakawa/exceptions.py
arakawa/file_store.py
arakawa/optional_libs.py
arakawa/settings.py
arakawa/types.py
arakawa/utils.py
arakawa/versioning.py
arakawa/blocks/__init__.py
arakawa/blocks/asset.py
arakawa/blocks/base.py
arakawa/blocks/controls.py
arakawa/blocks/layout.py
arakawa/blocks/misc_blocks.py
arakawa/blocks/mixins.py
arakawa/blocks/network.py
arakawa/blocks/text.py
arakawa/blocks/utils.py
arakawa/blocks/wrappers.py
arakawa/common/__init__.py
arakawa/common/datafiles.py
arakawa/common/df_processor.py
arakawa/common/utils.py
arakawa/ipython/__init__.py
arakawa/ipython/environment.py
arakawa/ipython/exceptions.py
arakawa/ipython/templates.py
arakawa/ipython/utils.py
arakawa/processors/__init__.py
arakawa/processors/api.py
arakawa/processors/processors.py
arakawa/processors/types.py
arakawa/resources/__init__.py
arakawa/resources/mime.types
arakawa/resources/html_templates/__init__.py
arakawa/resources/html_templates/head_chrome.html.j2
arakawa/resources/html_templates/ipython_base.html.j2
arakawa/resources/html_templates/ipython_template.html.j2
arakawa/resources/html_templates/local-report.css
arakawa/resources/html_templates/local-report.js
arakawa/resources/html_templates/local_template.html.j2
arakawa/view/__init__.py
arakawa/view/asset_writers.py
arakawa/view/pydantic_visitor.py
arakawa/view/view_blocks.py
arakawa/view/visitors.py
arakawa-0.3.0.dist-info/METADATA
arakawa-0.3.0.dist-info/WHEEL
arakawa-0.3.0.dist-info/licenses/LICENSE
arakawa-0.3.0.dist-info/RECORD
