Metadata-Version: 2.4
Name: arakawa
Version: 0.3.0
Summary: Build interactive reports in seconds using Python
Project-URL: Repository, https://github.com/ninoseki/arakawa/
Project-URL: Homepage, https://github.com/ninoseki/arakawa/
Project-URL: Documentation, https://ninoseki.github.io/arakawa/
License-File: LICENSE
Requires-Python: <4.0,>=3.10
Requires-Dist: altair~=6.0
Requires-Dist: base64io~=1.0
Requires-Dist: chardet~=5.2
Requires-Dist: dominate~=2.9
Requires-Dist: eval-type-backport~=0.2; python_version < '3.10'
Requires-Dist: ipynbname>=2024.1
Requires-Dist: ipython<10.0,>=8.13
Requires-Dist: jinja2~=3.0
Requires-Dist: loguru~=0.7
Requires-Dist: micawber~=0.5
Requires-Dist: multimethod~=2.0
Requires-Dist: pandas<4.0,>=2.2
Requires-Dist: pyarrow~=23.0
Requires-Dist: pydantic!=2.1.0,<3.0.0,>2.0.1
Requires-Dist: pyhumps~=3.8
Requires-Dist: semver~=3.0
Requires-Dist: typing-extensions~=4.12; python_version < '3.11'
Provides-Extra: all
Requires-Dist: bokeh<3.8.0,>=3.7.3; extra == 'all'
Requires-Dist: folium~=0.18; extra == 'all'
Requires-Dist: great-tables~=0.16; extra == 'all'
Requires-Dist: matplotlib~=3.9; extra == 'all'
Requires-Dist: networkx~=3.2; extra == 'all'
Requires-Dist: plotly~=6.0; extra == 'all'
Requires-Dist: polars~=1.0; extra == 'all'
Provides-Extra: dataframing
Requires-Dist: polars~=1.0; extra == 'dataframing'
Provides-Extra: network
Requires-Dist: networkx~=3.2; extra == 'network'
Provides-Extra: plotting
Requires-Dist: bokeh<3.8.0,>=3.7.3; extra == 'plotting'
Requires-Dist: folium~=0.18; extra == 'plotting'
Requires-Dist: matplotlib~=3.9; extra == 'plotting'
Requires-Dist: plotly~=6.0; extra == 'plotting'
Provides-Extra: tabling
Requires-Dist: great-tables~=0.16; extra == 'tabling'
